README.md
setup.cfg
setup.py
hnpy/__init__.py
hnpy/api.py
hnpy/const.py
hnpy/models.py
hnpy.egg-info/PKG-INFO
hnpy.egg-info/SOURCES.txt
hnpy.egg-info/dependency_links.txt
hnpy.egg-info/requires.txt
hnpy.egg-info/top_level.txt