Metadata-Version: 1.0
Name: hnpy
Version: 0.2.1
Summary: Yet another object-based Hacker News API wrapper for Python.
Home-page: https://github.com/jarhill0/hnpy
Author: jarhill0
Author-email: jarhill0@gmail.com
License: MIT
Keywords: hacker news api wrapper python3
Platform: UNKNOWN
